src/function_table.v
module funtable(
    input [3:0]b,
    input [5:0]p,
    output reg [2:0]q
);

reg [4:0]psm;

always @(*) begin
    q = 3'b000;
    case (b)
        4'b1000 : begin if (p[5])
            begin
                psm = ~p[4:0] + 1'b1;
                if(psm < 3) q = 3'b000;
                else if (psm < 7) q = 3'b101;
                else if (psm >= 7) q = 3'b110;
            end
            else begin
                psm = p[4:0];
                if (psm < 2) q = 3'b000;
                else if (psm < 6) q = 3'b001;
                else if (psm >= 6) q = 3'b010;
            end
        end  
        4'b1001 : begin if (p[5])
            begin
                psm = ~p[4:0] + 1'b1;
                if(psm < 4) q = 3'b000;
                else if (psm < 8) q = 3'b101;
                else if (psm >= 8) q = 3'b110;
            end
            else begin
                psm = p[4:0];
                if (psm < 3) q = 3'b000;
                else if (psm < 7) q = 3'b001;
                else if (psm >= 7) q = 3'b010;
            end
        end  
        4'b1010 :begin if (p[5])
            begin
                psm = ~p[4:0] + 1'b1;
                if(psm < 4) q = 3'b000;
                else if (psm < 9) q = 3'b101;
                else if (psm >= 9) q = 3'b110;
            end
            else begin
                psm = p[4:0];
                if (psm < 3) q = 3'b000;
                else if (psm < 8) q = 3'b001;
                else if (psm >= 8) q = 3'b010;
            end
        end  
        4'b1011 :begin if (p[5])
            begin
                psm = ~p[4:0] + 1'b1;
                if(psm < 4) q = 3'b000;
                else if (psm < 10) q = 3'b101;
                else if (psm >= 10) q = 3'b110;
            end
            else begin
                psm = p[4:0];
                if (psm < 3) q = 3'b000;
                else if (psm < 9) q = 3'b001;
                else if (psm >= 9) q = 3'b010;
            end
        end  
        4'b1100 :begin if (p[5])
            begin
                psm = ~p[4:0] + 1'b1;
                if(psm < 5) q = 3'b000;
                else if (psm < 11) q = 3'b101;
                else if (psm >= 11) q = 3'b110;
            end
            else begin
                psm = p[4:0];
                if (psm < 4) q = 3'b000;
                else if (psm < 10) q = 3'b001;
                else if (psm >= 10) q = 3'b010;
            end
        end  
        4'b1101 :begin if (p[5])
            begin
                psm = ~p[4:0] + 1'b1;
                if(psm < 5) q = 3'b000;
                else if (psm < 11) q = 3'b101;
                else if (psm >= 11) q = 3'b110;
            end
            else begin
                psm = p[4:0];
                if (psm < 4) q = 3'b000;
                else if (psm < 10) q = 3'b001;
                else if (psm >= 10) q = 3'b010;
            end
        end  
        4'b1110 :begin if (p[5])
            begin
                psm = ~p[4:0] + 1'b1;
                if(psm < 5) q = 3'b000;
                else if (psm < 12) q = 3'b101;
                else if (psm >= 12) q = 3'b110;
            end
            else begin
                psm = p[4:0];
                if (psm < 4) q = 3'b000;
                else if (psm < 11) q = 3'b001;
                else if (psm >= 11) q = 3'b010;
            end
        end  
        4'b1111 :begin if (p[5])
            begin
                psm = ~p[4:0] + 1'b1;
                if(psm < 6) q = 3'b000;
                else if (psm < 13) q = 3'b101;
                else if (psm >= 13) q = 3'b110;
            end
            else begin
                psm = p[4:0];
                if (psm < 5) q = 3'b000;
                else if (psm < 12) q = 3'b001;
                else if (psm >= 12) q = 3'b010;
            end
        end  
    endcase
end
endmodule

tb/fun_table_tb.v
`timescale 1ns/1ns

module fun_tbl_tb;
  reg [3:0] b;
  reg [5:0] p;
  wire [2:0] q;
  reg sw;
  integer i,j;
  
funtable srt4table(
  .b(b),
  .p(p), 
  .q(q)
);

initial begin
    $dumpfile("waveform.vcd");
    $dumpvars(0, fun_tbl_tb);
    i = 8;
    sw = 0;
    #10;
end

always @(*) begin
  if(~sw) begin
    testing();
    sw = 1;
  end
end

task testing();
  for(i = 8; i < 16; i = i+1'b1)
  begin 
    b = i;
    for (j = 0; j < 64; j = j + 1'b1)
    begin
      p = j;
      #10;
    end
  end
endtask

endmodule

tb/waveform.vcd
$date
	Thu Apr 20 10:33:23 2023
$end
$version
	Icarus Verilog
$end
$timescale
	1s
$end
$scope module fun_tbl_tb $end
$var wire 3 ! q [2:0] $end
$var reg 4 " b [3:0] $end
$var reg 6 # p [5:0] $end
$var reg 1 $ sw $end
$var integer 32 % i [31:0] $end
$var integer 32 & j [31:0] $end
$scope module srt4table $end
$var wire 4 ' b [3:0] $end
$var wire 6 ( p [5:0] $end
$var reg 5 ) psm [4:0] $end
$var reg 3 * q [2:0] $end
$upscope $end
$scope task testing $end
$upscope $end
$upscope $end
$enddefinitions $end
#0
$dumpvars
b0 *
b0 )
b0 (
b1000 '
b0 &
b1000 %
0$
b0 #
b1000 "
b0 !
$end
#10
b1 )
b1 #
b1 (
b1 &
#20
b1 !
b1 *
b10 )
b10 #
b10 (
b10 &
#30
b11 )
b1 !
b1 *
b11 #
b11 (
b11 &
#40
b100 )
b1 !
b1 *
b100 #
b100 (
b100 &
#50
b101 )
b1 !
b1 *
b101 #
b101 (
b101 &
#60
b110 )
b10 !
b10 *
b110 #
b110 (
b110 &
#70
b111 )
b10 !
b10 *
b111 #
b111 (
b111 &
#80
b1000 )
b10 !
b10 *
b1000 #
b1000 (
b1000 &
#90
b1001 )
b10 !
b10 *
b1001 #
b1001 (
b1001 &
#100
b1010 )
b10 !
b10 *
b1010 #
b1010 (
b1010 &
#110
b1011 )
b10 !
b10 *
b1011 #
b1011 (
b1011 &
#120
b1100 )
b10 !
b10 *
b1100 #
b1100 (
b1100 &
#130
b1101 )
b10 !
b10 *
b1101 #
b1101 (
b1101 &
#140
b1110 )
b10 !
b10 *
b1110 #
b1110 (
b1110 &
#150
b1111 )
b10 !
b10 *
b1111 #
b1111 (
b1111 &
#160
b10000 )
b10 !
b10 *
b10000 #
b10000 (
b10000 &
#170
b10001 )
b10 !
b10 *
b10001 #
b10001 (
b10001 &
#180
b10010 )
b10 !
b10 *
b10010 #
b10010 (
b10010 &
#190
b10011 )
b10 !
b10 *
b10011 #
b10011 (
b10011 &
#200
b10100 )
b10 !
b10 *
b10100 #
b10100 (
b10100 &
#210
b10101 )
b10 !
b10 *
b10101 #
b10101 (
b10101 &
#220
b10110 )
b10 !
b10 *
b10110 #
b10110 (
b10110 &
#230
b10111 )
b10 !
b10 *
b10111 #
b10111 (
b10111 &
#240
b11000 )
b10 !
b10 *
b11000 #
b11000 (
b11000 &
#250
b11001 )
b10 !
b10 *
b11001 #
b11001 (
b11001 &
#260
b11010 )
b10 !
b10 *
b11010 #
b11010 (
b11010 &
#270
b11011 )
b10 !
b10 *
b11011 #
b11011 (
b11011 &
#280
b11100 )
b10 !
b10 *
b11100 #
b11100 (
b11100 &
#290
b11101 )
b10 !
b10 *
b11101 #
b11101 (
b11101 &
#300
b11110 )
b10 !
b10 *
b11110 #
b11110 (
b11110 &
#310
b11111 )
b10 !
b10 *
b11111 #
b11111 (
b11111 &
#320
b0 )
b0 !
b0 *
b100000 #
b100000 (
b100000 &
#330
b110 !
b110 *
b11111 )
b100001 #
b100001 (
b100001 &
#340
b11110 )
b110 !
b110 *
b100010 #
b100010 (
b100010 &
#350
b11101 )
b110 !
b110 *
b100011 #
b100011 (
b100011 &
#360
b11100 )
b110 !
b110 *
b100100 #
b100100 (
b100100 &
#370
b11011 )
b110 !
b110 *
b100101 #
b100101 (
b100101 &
#380
b11010 )
b110 !
b110 *
b100110 #
b100110 (
b100110 &
#390
b11001 )
b110 !
b110 *
b100111 #
b100111 (
b100111 &
#400
b11000 )
b110 !
b110 *
b101000 #
b101000 (
b101000 &
#410
b10111 )
b110 !
b110 *
b101001 #
b101001 (
b101001 &
#420
b10110 )
b110 !
b110 *
b101010 #
b101010 (
b101010 &
#430
b10101 )
b110 !
b110 *
b101011 #
b101011 (
b101011 &
#440
b10100 )
b110 !
b110 *
b101100 #
b101100 (
b101100 &
#450
b10011 )
b110 !
b110 *
b101101 #
b101101 (
b101101 &
#460
b10010 )
b110 !
b110 *
b101110 #
b101110 (
b101110 &
#470
b10001 )
b110 !
b110 *
b101111 #
b101111 (
b101111 &
#480
b10000 )
b110 !
b110 *
b110000 #
b110000 (
b110000 &
#490
b1111 )
b110 !
b110 *
b110001 #
b110001 (
b110001 &
#500
b1110 )
b110 !
b110 *
b110010 #
b110010 (
b110010 &
#510
b1101 )
b110 !
b110 *
b110011 #
b110011 (
b110011 &
#520
b1100 )
b110 !
b110 *
b110100 #
b110100 (
b110100 &
#530
b1011 )
b110 !
b110 *
b110101 #
b110101 (
b110101 &
#540
b1010 )
b110 !
b110 *
b110110 #
b110110 (
b110110 &
#550
b1001 )
b110 !
b110 *
b110111 #
b110111 (
b110111 &
#560
b1000 )
b110 !
b110 *
b111000 #
b111000 (
b111000 &
#570
b111 )
b110 !
b110 *
b111001 #
b111001 (
b111001 &
#580
b110 )
b101 !
b101 *
b111010 #
b111010 (
b111010 &
#590
b101 )
b101 !
b101 *
b111011 #
b111011 (
b111011 &
#600
b100 )
b101 !
b101 *
b111100 #
b111100 (
b111100 &
#610
b11 )
b101 !
b101 *
b111101 #
b111101 (
b111101 &
#620
b10 )
b0 !
b0 *
b111110 #
b111110 (
b111110 &
#630
b1 )
b111111 #
b111111 (
b111111 &
#640
b0 )
b0 #
b0 (
b1001 "
b1001 '
b1001 %
b0 &
#650
b1 )
b1 #
b1 (
b1 &
#660
b10 )
b10 #
b10 (
b10 &
#670
b1 !
b1 *
b11 )
b11 #
b11 (
b11 &
#680
b100 )
b1 !
b1 *
b100 #
b100 (
b100 &
#690
b101 )
b1 !
b1 *
b101 #
b101 (
b101 &
#700
b110 )
b1 !
b1 *
b110 #
b110 (
b110 &
#710
b111 )
b10 !
b10 *
b111 #
b111 (
b111 &
#720
b1000 )
b10 !
b10 *
b1000 #
b1000 (
b1000 &
#730
b1001 )
b10 !
b10 *
b1001 #
b1001 (
b1001 &
#740
b1010 )
b10 !
b10 *
b1010 #
b1010 (
b1010 &
#750
b1011 )
b10 !
b10 *
b1011 #
b1011 (
b1011 &
#760
b1100 )
b10 !
b10 *
b1100 #
b1100 (
b1100 &
#770
b1101 )
b10 !
b10 *
b1101 #
b1101 (
b1101 &
#780
b1110 )
b10 !
b10 *
b1110 #
b1110 (
b1110 &
#790
b1111 )
b10 !
b10 *
b1111 #
b1111 (
b1111 &
#800
b10000 )
b10 !
b10 *
b10000 #
b10000 (
b10000 &
#810
b10001 )
b10 !
b10 *
b10001 #
b10001 (
b10001 &
#820
b10010 )
b10 !
b10 *
b10010 #
b10010 (
b10010 &
#830
b10011 )
b10 !
b10 *
b10011 #
b10011 (
b10011 &
#840
b10100 )
b10 !
b10 *
b10100 #
b10100 (
b10100 &
#850
b10101 )
b10 !
b10 *
b10101 #
b10101 (
b10101 &
#860
b10110 )
b10 !
b10 *
b10110 #
b10110 (
b10110 &
#870
b10111 )
b10 !
b10 *
b10111 #
b10111 (
b10111 &
#880
b11000 )
b10 !
b10 *
b11000 #
b11000 (
b11000 &
#890
b11001 )
b10 !
b10 *
b11001 #
b11001 (
b11001 &
#900
b11010 )
b10 !
b10 *
b11010 #
b11010 (
b11010 &
#910
b11011 )
b10 !
b10 *
b11011 #
b11011 (
b11011 &
#920
b11100 )
b10 !
b10 *
b11100 #
b11100 (
b11100 &
#930
b11101 )
b10 !
b10 *
b11101 #
b11101 (
b11101 &
#940
b11110 )
b10 !
b10 *
b11110 #
b11110 (
b11110 &
#950
b11111 )
b10 !
b10 *
b11111 #
b11111 (
b11111 &
#960
b0 )
b0 !
b0 *
b100000 #
b100000 (
b100000 &
#970
b110 !
b110 *
b11111 )
b100001 #
b100001 (
b100001 &
#980
b11110 )
b110 !
b110 *
b100010 #
b100010 (
b100010 &
#990
b11101 )
b110 !
b110 *
b100011 #
b100011 (
b100011 &
#1000
b11100 )
b110 !
b110 *
b100100 #
b100100 (
b100100 &
#1010
b11011 )
b110 !
b110 *
b100101 #
b100101 (
b100101 &
#1020
b11010 )
b110 !
b110 *
b100110 #
b100110 (
b100110 &
#1030
b11001 )
b110 !
b110 *
b100111 #
b100111 (
b100111 &
#1040
b11000 )
b110 !
b110 *
b101000 #
b101000 (
b101000 &
#1050
b10111 )
b110 !
b110 *
b101001 #
b101001 (
b101001 &
#1060
b10110 )
b110 !
b110 *
b101010 #
b101010 (
b101010 &
#1070
b10101 )
b110 !
b110 *
b101011 #
b101011 (
b101011 &
#1080
b10100 )
b110 !
b110 *
b101100 #
b101100 (
b101100 &
#1090
b10011 )
b110 !
b110 *
b101101 #
b101101 (
b101101 &
#1100
b10010 )
b110 !
b110 *
b101110 #
b101110 (
b101110 &
#1110
b10001 )
b110 !
b110 *
b101111 #
b101111 (
b101111 &
#1120
b10000 )
b110 !
b110 *
b110000 #
b110000 (
b110000 &
#1130
b1111 )
b110 !
b110 *
b110001 #
b110001 (
b110001 &
#1140
b1110 )
b110 !
b110 *
b110010 #
b110010 (
b110010 &
#1150
b1101 )
b110 !
b110 *
b110011 #
b110011 (
b110011 &
#1160
b1100 )
b110 !
b110 *
b110100 #
b110100 (
b110100 &
#1170
b1011 )
b110 !
b110 *
b110101 #
b110101 (
b110101 &
#1180
b1010 )
b110 !
b110 *
b110110 #
b110110 (
b110110 &
#1190
b1001 )
b110 !
b110 *
b110111 #
b110111 (
b110111 &
#1200
b1000 )
b110 !
b110 *
b111000 #
b111000 (
b111000 &
#1210
b111 )
b101 !
b101 *
b111001 #
b111001 (
b111001 &
#1220
b110 )
b101 !
b101 *
b111010 #
b111010 (
b111010 &
#1230
b101 )
b101 !
b101 *
b111011 #
b111011 (
b111011 &
#1240
b100 )
b101 !
b101 *
b111100 #
b111100 (
b111100 &
#1250
b11 )
b0 !
b0 *
b111101 #
b111101 (
b111101 &
#1260
b10 )
b111110 #
b111110 (
b111110 &
#1270
b1 )
b111111 #
b111111 (
b111111 &
#1280
b0 )
b0 #
b0 (
b1010 "
b1010 '
b1010 %
b0 &
#1290
b1 )
b1 #
b1 (
b1 &
#1300
b10 )
b10 #
b10 (
b10 &
#1310
b1 !
b1 *
b11 )
b11 #
b11 (
b11 &
#1320
b100 )
b1 !
b1 *
b100 #
b100 (
b100 &
#1330
b101 )
b1 !
b1 *
b101 #
b101 (
b101 &
#1340
b110 )
b1 !
b1 *
b110 #
b110 (
b110 &
#1350
b111 )
b1 !
b1 *
b111 #
b111 (
b111 &
#1360
b1000 )
b10 !
b10 *
b1000 #
b1000 (
b1000 &
#1370
b1001 )
b10 !
b10 *
b1001 #
b1001 (
b1001 &
#1380
b1010 )
b10 !
b10 *
b1010 #
b1010 (
b1010 &
#1390
b1011 )
b10 !
b10 *
b1011 #
b1011 (
b1011 &
#1400
b1100 )
b10 !
b10 *
b1100 #
b1100 (
b1100 &
#1410
b1101 )
b10 !
b10 *
b1101 #
b1101 (
b1101 &
#1420
b1110 )
b10 !
b10 *
b1110 #
b1110 (
b1110 &
#1430
b1111 )
b10 !
b10 *
b1111 #
b1111 (
b1111 &
#1440
b10000 )
b10 !
b10 *
b10000 #
b10000 (
b10000 &
#1450
b10001 )
b10 !
b10 *
b10001 #
b10001 (
b10001 &
#1460
b10010 )
b10 !
b10 *
b10010 #
b10010 (
b10010 &
#1470
b10011 )
b10 !
b10 *
b10011 #
b10011 (
b10011 &
#1480
b10100 )
b10 !
b10 *
b10100 #
b10100 (
b10100 &
#1490
b10101 )
b10 !
b10 *
b10101 #
b10101 (
b10101 &
#1500
b10110 )
b10 !
b10 *
b10110 #
b10110 (
b10110 &
#1510
b10111 )
b10 !
b10 *
b10111 #
b10111 (
b10111 &
#1520
b11000 )
b10 !
b10 *
b11000 #
b11000 (
b11000 &
#1530
b11001 )
b10 !
b10 *
b11001 #
b11001 (
b11001 &
#1540
b11010 )
b10 !
b10 *
b11010 #
b11010 (
b11010 &
#1550
b11011 )
b10 !
b10 *
b11011 #
b11011 (
b11011 &
#1560
b11100 )
b10 !
b10 *
b11100 #
b11100 (
b11100 &
#1570
b11101 )
b10 !
b10 *
b11101 #
b11101 (
b11101 &
#1580
b11110 )
b10 !
b10 *
b11110 #
b11110 (
b11110 &
#1590
b11111 )
b10 !
b10 *
b11111 #
b11111 (
b11111 &
#1600
b0 )
b0 !
b0 *
b100000 #
b100000 (
b100000 &
#1610
b110 !
b110 *
b11111 )
b100001 #
b100001 (
b100001 &
#1620
b11110 )
b110 !
b110 *
b100010 #
b100010 (
b100010 &
#1630
b11101 )
b110 !
b110 *
b100011 #
b100011 (
b100011 &
#1640
b11100 )
b110 !
b110 *
b100100 #
b100100 (
b100100 &
#1650
b11011 )
b110 !
b110 *
b100101 #
b100101 (
b100101 &
#1660
b11010 )
b110 !
b110 *
b100110 #
b100110 (
b100110 &
#1670
b11001 )
b110 !
b110 *
b100111 #
b100111 (
b100111 &
#1680
b11000 )
b110 !
b110 *
b101000 #
b101000 (
b101000 &
#1690
b10111 )
b110 !
b110 *
b101001 #
b101001 (
b101001 &
#1700
b10110 )
b110 !
b110 *
b101010 #
b101010 (
b101010 &
#1710
b10101 )
b110 !
b110 *
b101011 #
b101011 (
b101011 &
#1720
b10100 )
b110 !
b110 *
b101100 #
b101100 (
b101100 &
#1730
b10011 )
b110 !
b110 *
b101101 #
b101101 (
b101101 &
#1740
b10010 )
b110 !
b110 *
b101110 #
b101110 (
b101110 &
#1750
b10001 )
b110 !
b110 *
b101111 #
b101111 (
b101111 &
#1760
b10000 )
b110 !
b110 *
b110000 #
b110000 (
b110000 &
#1770
b1111 )
b110 !
b110 *
b110001 #
b110001 (
b110001 &
#1780
b1110 )
b110 !
b110 *
b110010 #
b110010 (
b110010 &
#1790
b1101 )
b110 !
b110 *
b110011 #
b110011 (
b110011 &
#1800
b1100 )
b110 !
b110 *
b110100 #
b110100 (
b110100 &
#1810
b1011 )
b110 !
b110 *
b110101 #
b110101 (
b110101 &
#1820
b1010 )
b110 !
b110 *
b110110 #
b110110 (
b110110 &
#1830
b1001 )
b110 !
b110 *
b110111 #
b110111 (
b110111 &
#1840
b1000 )
b101 !
b101 *
b111000 #
b111000 (
b111000 &
#1850
b111 )
b101 !
b101 *
b111001 #
b111001 (
b111001 &
#1860
b110 )
b101 !
b101 *
b111010 #
b111010 (
b111010 &
#1870
b101 )
b101 !
b101 *
b111011 #
b111011 (
b111011 &
#1880
b100 )
b101 !
b101 *
b111100 #
b111100 (
b111100 &
#1890
b11 )
b0 !
b0 *
b111101 #
b111101 (
b111101 &
#1900
b10 )
b111110 #
b111110 (
b111110 &
#1910
b1 )
b111111 #
b111111 (
b111111 &
#1920
b0 )
b0 #
b0 (
b1011 "
b1011 '
b1011 %
b0 &
#1930
b1 )
b1 #
b1 (
b1 &
#1940
b10 )
b10 #
b10 (
b10 &
#1950
b1 !
b1 *
b11 )
b11 #
b11 (
b11 &
#1960
b100 )
b1 !
b1 *
b100 #
b100 (
b100 &
#1970
b101 )
b1 !
b1 *
b101 #
b101 (
b101 &
#1980
b110 )
b1 !
b1 *
b110 #
b110 (
b110 &
#1990
b111 )
b1 !
b1 *
b111 #
b111 (
b111 &
#2000
b1000 )
b1 !
b1 *
b1000 #
b1000 (
b1000 &
#2010
b1001 )
b10 !
b10 *
b1001 #
b1001 (
b1001 &
#2020
b1010 )
b10 !
b10 *
b1010 #
b1010 (
b1010 &
#2030
b1011 )
b10 !
b10 *
b1011 #
b1011 (
b1011 &
#2040
b1100 )
b10 !
b10 *
b1100 #
b1100 (
b1100 &
#2050
b1101 )
b10 !
b10 *
b1101 #
b1101 (
b1101 &
#2060
b1110 )
b10 !
b10 *
b1110 #
b1110 (
b1110 &
#2070
b1111 )
b10 !
b10 *
b1111 #
b1111 (
b1111 &
#2080
b10000 )
b10 !
b10 *
b10000 #
b10000 (
b10000 &
#2090
b10001 )
b10 !
b10 *
b10001 #
b10001 (
b10001 &
#2100
b10010 )
b10 !
b10 *
b10010 #
b10010 (
b10010 &
#2110
b10011 )
b10 !
b10 *
b10011 #
b10011 (
b10011 &
#2120
b10100 )
b10 !
b10 *
b10100 #
b10100 (
b10100 &
#2130
b10101 )
b10 !
b10 *
b10101 #
b10101 (
b10101 &
#2140
b10110 )
b10 !
b10 *
b10110 #
b10110 (
b10110 &
#2150
b10111 )
b10 !
b10 *
b10111 #
b10111 (
b10111 &
#2160
b11000 )
b10 !
b10 *
b11000 #
b11000 (
b11000 &
#2170
b11001 )
b10 !
b10 *
b11001 #
b11001 (
b11001 &
#2180
b11010 )
b10 !
b10 *
b11010 #
b11010 (
b11010 &
#2190
b11011 )
b10 !
b10 *
b11011 #
b11011 (
b11011 &
#2200
b11100 )
b10 !
b10 *
b11100 #
b11100 (
b11100 &
#2210
b11101 )
b10 !
b10 *
b11101 #
b11101 (
b11101 &
#2220
b11110 )
b10 !
b10 *
b11110 #
b11110 (
b11110 &
#2230
b11111 )
b10 !
b10 *
b11111 #
b11111 (
b11111 &
#2240
b0 )
b0 !
b0 *
b100000 #
b100000 (
b100000 &
#2250
b110 !
b110 *
b11111 )
b100001 #
b100001 (
b100001 &
#2260
b11110 )
b110 !
b110 *
b100010 #
b100010 (
b100010 &
#2270
b11101 )
b110 !
b110 *
b100011 #
b100011 (
b100011 &
#2280
b11100 )
b110 !
b110 *
b100100 #
b100100 (
b100100 &
#2290
b11011 )
b110 !
b110 *
b100101 #
b100101 (
b100101 &
#2300
b11010 )
b110 !
b110 *
b100110 #
b100110 (
b100110 &
#2310
b11001 )
b110 !
b110 *
b100111 #
b100111 (
b100111 &
#2320
b11000 )
b110 !
b110 *
b101000 #
b101000 (
b101000 &
#2330
b10111 )
b110 !
b110 *
b101001 #
b101001 (
b101001 &
#2340
b10110 )
b110 !
b110 *
b101010 #
b101010 (
b101010 &
#2350
b10101 )
b110 !
b110 *
b101011 #
b101011 (
b101011 &
#2360
b10100 )
b110 !
b110 *
b101100 #
b101100 (
b101100 &
#2370
b10011 )
b110 !
b110 *
b101101 #
b101101 (
b101101 &
#2380
b10010 )
b110 !
b110 *
b101110 #
b101110 (
b101110 &
#2390
b10001 )
b110 !
b110 *
b101111 #
b101111 (
b101111 &
#2400
b10000 )
b110 !
b110 *
b110000 #
b110000 (
b110000 &
#2410
b1111 )
b110 !
b110 *
b110001 #
b110001 (
b110001 &
#2420
b1110 )
b110 !
b110 *
b110010 #
b110010 (
b110010 &
#2430
b1101 )
b110 !
b110 *
b110011 #
b110011 (
b110011 &
#2440
b1100 )
b110 !
b110 *
b110100 #
b110100 (
b110100 &
#2450
b1011 )
b110 !
b110 *
b110101 #
b110101 (
b110101 &
#2460
b1010 )
b110 !
b110 *
b110110 #
b110110 (
b110110 &
#2470
b1001 )
b101 !
b101 *
b110111 #
b110111 (
b110111 &
#2480
b1000 )
b101 !
b101 *
b111000 #
b111000 (
b111000 &
#2490
b111 )
b101 !
b101 *
b111001 #
b111001 (
b111001 &
#2500
b110 )
b101 !
b101 *
b111010 #
b111010 (
b111010 &
#2510
b101 )
b101 !
b101 *
b111011 #
b111011 (
b111011 &
#2520
b100 )
b101 !
b101 *
b111100 #
b111100 (
b111100 &
#2530
b11 )
b0 !
b0 *
b111101 #
b111101 (
b111101 &
#2540
b10 )
b111110 #
b111110 (
b111110 &
#2550
b1 )
b111111 #
b111111 (
b111111 &
#2560
b0 )
b0 #
b0 (
b1100 "
b1100 '
b1100 %
b0 &
#2570
b1 )
b1 #
b1 (
b1 &
#2580
b10 )
b10 #
b10 (
b10 &
#2590
b11 )
b11 #
b11 (
b11 &
#2600
b1 !
b1 *
b100 )
b100 #
b100 (
b100 &
#2610
b101 )
b1 !
b1 *
b101 #
b101 (
b101 &
#2620
b110 )
b1 !
b1 *
b110 #
b110 (
b110 &
#2630
b111 )
b1 !
b1 *
b111 #
b111 (
b111 &
#2640
b1000 )
b1 !
b1 *
b1000 #
b1000 (
b1000 &
#2650
b1001 )
b1 !
b1 *
b1001 #
b1001 (
b1001 &
#2660
b1010 )
b10 !
b10 *
b1010 #
b1010 (
b1010 &
#2670
b1011 )
b10 !
b10 *
b1011 #
b1011 (
b1011 &
#2680
b1100 )
b10 !
b10 *
b1100 #
b1100 (
b1100 &
#2690
b1101 )
b10 !
b10 *
b1101 #
b1101 (
b1101 &
#2700
b1110 )
b10 !
b10 *
b1110 #
b1110 (
b1110 &
#2710
b1111 )
b10 !
b10 *
b1111 #
b1111 (
b1111 &
#2720
b10000 )
b10 !
b10 *
b10000 #
b10000 (
b10000 &
#2730
b10001 )
b10 !
b10 *
b10001 #
b10001 (
b10001 &
#2740
b10010 )
b10 !
b10 *
b10010 #
b10010 (
b10010 &
#2750
b10011 )
b10 !
b10 *
b10011 #
b10011 (
b10011 &
#2760
b10100 )
b10 !
b10 *
b10100 #
b10100 (
b10100 &
#2770
b10101 )
b10 !
b10 *
b10101 #
b10101 (
b10101 &
#2780
b10110 )
b10 !
b10 *
b10110 #
b10110 (
b10110 &
#2790
b10111 )
b10 !
b10 *
b10111 #
b10111 (
b10111 &
#2800
b11000 )
b10 !
b10 *
b11000 #
b11000 (
b11000 &
#2810
b11001 )
b10 !
b10 *
b11001 #
b11001 (
b11001 &
#2820
b11010 )
b10 !
b10 *
b11010 #
b11010 (
b11010 &
#2830
b11011 )
b10 !
b10 *
b11011 #
b11011 (
b11011 &
#2840
b11100 )
b10 !
b10 *
b11100 #
b11100 (
b11100 &
#2850
b11101 )
b10 !
b10 *
b11101 #
b11101 (
b11101 &
#2860
b11110 )
b10 !
b10 *
b11110 #
b11110 (
b11110 &
#2870
b11111 )
b10 !
b10 *
b11111 #
b11111 (
b11111 &
#2880
b0 )
b0 !
b0 *
b100000 #
b100000 (
b100000 &
#2890
b110 !
b110 *
b11111 )
b100001 #
b100001 (
b100001 &
#2900
b11110 )
b110 !
b110 *
b100010 #
b100010 (
b100010 &
#2910
b11101 )
b110 !
b110 *
b100011 #
b100011 (
b100011 &
#2920
b11100 )
b110 !
b110 *
b100100 #
b100100 (
b100100 &
#2930
b11011 )
b110 !
b110 *
b100101 #
b100101 (
b100101 &
#2940
b11010 )
b110 !
b110 *
b100110 #
b100110 (
b100110 &
#2950
b11001 )
b110 !
b110 *
b100111 #
b100111 (
b100111 &
#2960
b11000 )
b110 !
b110 *
b101000 #
b101000 (
b101000 &
#2970
b10111 )
b110 !
b110 *
b101001 #
b101001 (
b101001 &
#2980
b10110 )
b110 !
b110 *
b101010 #
b101010 (
b101010 &
#2990
b10101 )
b110 !
b110 *
b101011 #
b101011 (
b101011 &
#3000
b10100 )
b110 !
b110 *
b101100 #
b101100 (
b101100 &
#3010
b10011 )
b110 !
b110 *
b101101 #
b101101 (
b101101 &
#3020
b10010 )
b110 !
b110 *
b101110 #
b101110 (
b101110 &
#3030
b10001 )
b110 !
b110 *
b101111 #
b101111 (
b101111 &
#3040
b10000 )
b110 !
b110 *
b110000 #
b110000 (
b110000 &
#3050
b1111 )
b110 !
b110 *
b110001 #
b110001 (
b110001 &
#3060
b1110 )
b110 !
b110 *
b110010 #
b110010 (
b110010 &
#3070
b1101 )
b110 !
b110 *
b110011 #
b110011 (
b110011 &
#3080
b1100 )
b110 !
b110 *
b110100 #
b110100 (
b110100 &
#3090
b1011 )
b110 !
b110 *
b110101 #
b110101 (
b110101 &
#3100
b1010 )
b101 !
b101 *
b110110 #
b110110 (
b110110 &
#3110
b1001 )
b101 !
b101 *
b110111 #
b110111 (
b110111 &
#3120
b1000 )
b101 !
b101 *
b111000 #
b111000 (
b111000 &
#3130
b111 )
b101 !
b101 *
b111001 #
b111001 (
b111001 &
#3140
b110 )
b101 !
b101 *
b111010 #
b111010 (
b111010 &
#3150
b101 )
b101 !
b101 *
b111011 #
b111011 (
b111011 &
#3160
b100 )
b0 !
b0 *
b111100 #
b111100 (
b111100 &
#3170
b11 )
b111101 #
b111101 (
b111101 &
#3180
b10 )
b111110 #
b111110 (
b111110 &
#3190
b1 )
b111111 #
b111111 (
b111111 &
#3200
b0 )
b0 #
b0 (
b1101 "
b1101 '
b1101 %
b0 &
#3210
b1 )
b1 #
b1 (
b1 &
#3220
b10 )
b10 #
b10 (
b10 &
#3230
b11 )
b11 #
b11 (
b11 &
#3240
b1 !
b1 *
b100 )
b100 #
b100 (
b100 &
#3250
b101 )
b1 !
b1 *
b101 #
b101 (
b101 &
#3260
b110 )
b1 !
b1 *
b110 #
b110 (
b110 &
#3270
b111 )
b1 !
b1 *
b111 #
b111 (
b111 &
#3280
b1000 )
b1 !
b1 *
b1000 #
b1000 (
b1000 &
#3290
b1001 )
b1 !
b1 *
b1001 #
b1001 (
b1001 &
#3300
b1010 )
b10 !
b10 *
b1010 #
b1010 (
b1010 &
#3310
b1011 )
b10 !
b10 *
b1011 #
b1011 (
b1011 &
#3320
b1100 )
b10 !
b10 *
b1100 #
b1100 (
b1100 &
#3330
b1101 )
b10 !
b10 *
b1101 #
b1101 (
b1101 &
#3340
b1110 )
b10 !
b10 *
b1110 #
b1110 (
b1110 &
#3350
b1111 )
b10 !
b10 *
b1111 #
b1111 (
b1111 &
#3360
b10000 )
b10 !
b10 *
b10000 #
b10000 (
b10000 &
#3370
b10001 )
b10 !
b10 *
b10001 #
b10001 (
b10001 &
#3380
b10010 )
b10 !
b10 *
b10010 #
b10010 (
b10010 &
#3390
b10011 )
b10 !
b10 *
b10011 #
b10011 (
b10011 &
#3400
b10100 )
b10 !
b10 *
b10100 #
b10100 (
b10100 &
#3410
b10101 )
b10 !
b10 *
b10101 #
b10101 (
b10101 &
#3420
b10110 )
b10 !
b10 *
b10110 #
b10110 (
b10110 &
#3430
b10111 )
b10 !
b10 *
b10111 #
b10111 (
b10111 &
#3440
b11000 )
b10 !
b10 *
b11000 #
b11000 (
b11000 &
#3450
b11001 )
b10 !
b10 *
b11001 #
b11001 (
b11001 &
#3460
b11010 )
b10 !
b10 *
b11010 #
b11010 (
b11010 &
#3470
b11011 )
b10 !
b10 *
b11011 #
b11011 (
b11011 &
#3480
b11100 )
b10 !
b10 *
b11100 #
b11100 (
b11100 &
#3490
b11101 )
b10 !
b10 *
b11101 #
b11101 (
b11101 &
